[{"Name":"Kinny Luten","AccountNumber":"7129764384","Balance":"04"},
{"Name":"Chrisy Meth","AccountNumber":"5491978663","Balance":"66464"},
{"Name":"Hartwell Rizon","AccountNumber":"4610947277","Balance":"59"},
{"Name":"Briano Bysouth","AccountNumber":"0986173045","Balance":"1695"},
{"Name":"Thaddus Esseby","AccountNumber":"3257291264","Balance":"2360"},
{"Name":"Micah Glentz","AccountNumber":"4162534322","Balance":"1"},
{"Name":"Bevin Valens-Smith","AccountNumber":"2591383278","Balance":"1041"},
{"Name":"Valene Beecham","AccountNumber":"6810109161","Balance":"16911"},
{"Name":"Wilona Bennet","AccountNumber":"7286282832","Balance":"9038"},
{"Name":"Charlot Court","AccountNumber":"2646797591","Balance":"1048"}]